cdse_dl/__init__.py
cdse_dl/auth.py
cdse_dl/download.py
cdse_dl/subscriptions.py
cdse_dl/types.py
cdse_dl/utils.py
cdse_dl/odata/__init__.py
cdse_dl/odata/attributes.py
cdse_dl/odata/filter.py
cdse_dl/odata/search.py
cdse_dl/odata/utils.py
cdse_dl/opensearch/search.py
cdse_dl-0.1.0a1.dist-info/LICENSE
cdse_dl-0.1.0a1.dist-info/METADATA
cdse_dl-0.1.0a1.dist-info/WHEEL
cdse_dl-0.1.0a1.dist-info/top_level.txt
cdse_dl-0.1.0a1.dist-info/RECORD
