Metadata-Version: 2.1
Name: cdse-dl
Version: 0.1.0a1
Summary: Clients for interacting with Copernicus Data Space Ecosystem
Requires-Python: >=3.10
License-File: LICENSE
Requires-Dist: blake3 >=0.3.1
Requires-Dist: python-dateutil >=2.7.0
Requires-Dist: requests >=2.28.1
Requires-Dist: s3fs >=2022.5.0
Requires-Dist: shapely >=2.0.4
Requires-Dist: tinynetrc >=1.3.1
Requires-Dist: tqdm >=4.63.2
